CHANGELOG.txt
LICENSE.txt
MANIFEST.in
README.txt
__init__.py
decisionboundary.py
setup.py
clfsdecisionboundary.egg-info/PKG-INFO
clfsdecisionboundary.egg-info/SOURCES.txt
clfsdecisionboundary.egg-info/dependency_links.txt
clfsdecisionboundary.egg-info/top_level.txt
decision_boundary/__init__.py
decision_boundary/decisionboundary.py