Metadata-Version: 1.1
Name: clfsdecisionboundary
Version: 0.0.1
Summary: Plot decision boundary for classification
Home-page: UNKNOWN
Author: Anubhav Sanyal
Author-email: anubhavsanyal9@gmail.com
License: MIT
Keywords: decision boundary
Platform: UNKNOWN
Classifier: Development Status :: 5 - Production/Stable
Classifier: Intended Audience :: Education
Classifier: Operating System :: Microsoft :: Windows :: Windows 10
Classifier: License :: OSI Approved :: MIT License
Classifier: Programming Language :: Python :: 3
